onert/__init__.py
onert/common/__init__.py
onert/common/basesession.py
onert/experimental/__init__.py
onert/experimental/train/__init__.py
onert/experimental/train/dataloader.py
onert/experimental/train/session.py
onert/experimental/train/losses/__init__.py
onert/experimental/train/losses/cce.py
onert/experimental/train/losses/loss.py
onert/experimental/train/losses/mse.py
onert/experimental/train/losses/registry.py
onert/experimental/train/metrics/__init__.py
onert/experimental/train/metrics/categorical_accuracy.py
onert/experimental/train/metrics/metric.py
onert/experimental/train/metrics/registry.py
onert/experimental/train/optimizer/__init__.py
onert/experimental/train/optimizer/adam.py
onert/experimental/train/optimizer/optimizer.py
onert/experimental/train/optimizer/registry.py
onert/experimental/train/optimizer/sgd.py
onert/infer/__init__.py
onert/infer/session.py
onert/native/libnnfw_api_pybind.so
onert/native/libonert.so
onert/native/nnfw/libonert_core.so
onert/native/nnfw/backend/libbackend_cpu.so
onert/native/nnfw/backend/libbackend_ruy.so
onert/native/nnfw/backend/libbackend_train.so
onert-0.1.0.dist-info/METADATA
onert-0.1.0.dist-info/WHEEL
onert-0.1.0.dist-info/top_level.txt
onert-0.1.0.dist-info/RECORD
