Metadata-Version: 2.4
Name: onert
Version: 0.1.0
Summary: onert API binding
Home-page: https://github.com/Samsung/ONE
License: Apache-2.0, MIT, BSD-2-Clause, BSD-3-Clause, Mozilla Public License 2.0
Requires-Dist: numpy>=1.19
Dynamic: description
Dynamic: home-page
Dynamic: license
Dynamic: requires-dist
Dynamic: summary
